mkdocs_page_pdf/__init__.py
mkdocs_page_pdf/plugin.py
mkdocs_page_pdf-0.4.0.dist-info/LICENSE
mkdocs_page_pdf-0.4.0.dist-info/METADATA
mkdocs_page_pdf-0.4.0.dist-info/WHEEL
mkdocs_page_pdf-0.4.0.dist-info/entry_points.txt
mkdocs_page_pdf-0.4.0.dist-info/top_level.txt
mkdocs_page_pdf-0.4.0.dist-info/RECORD
