Metadata-Version: 2.1
Name: mkdocs-page-pdf
Version: 0.4.0
Summary: Generate a PDF file for each MkDocs page
Home-page: https://github.com/brospars/mkdocs-page-pdf
Author: brospars
Author-email: 
License: MIT
Keywords: mkdocs pdf pyppeteer chrome headless page
Classifier: Development Status :: 4 - Beta
Classifier: Intended Audience :: Developers
Classifier: Intended Audience :: Information Technology
Classifier: License :: OSI Approved :: MIT License
Classifier: Programming Language :: Python
Classifier: Programming Language :: Python :: 3 :: Only
Classifier: Programming Language :: Python :: 3.6
Classifier: Programming Language :: Python :: 3.7
Classifier: Programming Language :: Python :: 3.8
Classifier: Programming Language :: Python :: 3.9
Requires-Python: >=3.6
License-File: LICENSE
Requires-Dist: mkdocs>=1.1
Requires-Dist: playwright>=1.57
Requires-Dist: asyncio>=1.5
Requires-Dist: nest-asyncio>=1.5
